{
    "pipes": [],
    "interfaces": [
        {
            "name": "User",
            "id": "interface-User-9c7e5f1bbbab702cb032307d130876cb68969b0cd4eedef32a0c8cad8081a54e5f8f577ed6ad4539c1b99a1d246cb34031d198c2ea8eba440e64e91b14f01fdc",
            "file": "stories/User.ts",
            "deprecated": false,
            "deprecationMessage": "",
            "type": "interface",
            "sourceCode": "export interface User {}\n",
            "properties": [],
            "indexSignatures": [],
            "methods": []
        }
    ],
    "injectables": [
        {
            "name": "PatternLibService",
            "id": "injectable-PatternLibService-96b81df60554001546d6f323fe084da5b909deb4e681b749837286ed71051a7dd6b2e724275029d0a564ab8d626694317c60e1520fbc41f88d47c5ce3684d83f",
            "file": "projects/pattern-lib/src/lib/pattern-lib.service.ts",
            "properties": [],
            "methods": [],
            "deprecated": false,
            "deprecationMessage": "",
            "description": "",
            "rawdescription": "\n",
            "sourceCode": "import { Injectable } from '@angular/core';\n\n@Injectable({\n  providedIn: 'root'\n})\nexport class PatternLibService {\n\n  constructor() { }\n}\n",
            "constructorObj": {
                "name": "constructor",
                "description": "",
                "deprecated": false,
                "deprecationMessage": "",
                "args": [],
                "line": 6
            },
            "type": "injectable"
        }
    ],
    "guards": [],
    "interceptors": [],
    "classes": [],
    "directives": [],
    "components": [
        {
            "name": "ButtonComponent",
            "id": "component-ButtonComponent-4ef205c97a334c309aa4001c8ab4a6d9571dcae18d0e85aaf0d367467ab5d3a9f13ab3573726f1fcb409bc9b49894dadfb80b1bbe1b6ba7041455ad9d4922004",
            "file": "stories/button.component.ts",
            "encapsulation": [],
            "entryComponents": [],
            "inputs": [],
            "outputs": [],
            "providers": [],
            "selector": "storybook-button",
            "styleUrls": [
                "./button.css"
            ],
            "styles": [],
            "template": "<button   type=\"button\"\n   (click)=\"onClick.emit($event)\"\n   [ngClass]=\"classes\"\n   [ngStyle]=\"{ 'background-color': backgroundColor }\"\n >\n   {{ label }}\n </button>",
            "templateUrl": [],
            "viewProviders": [],
            "inputsClass": [
                {
                    "name": "backgroundColor",
                    "deprecated": false,
                    "deprecationMessage": "",
                    "rawdescription": "\n\nWhat background color to use\n",
                    "description": "<p>What background color to use</p>\n",
                    "line": 26,
                    "type": "string",
                    "decorators": []
                },
                {
                    "name": "label",
                    "defaultValue": "'Button'",
                    "deprecated": false,
                    "deprecationMessage": "",
                    "jsdoctags": [
                        {
                            "pos": 711,
                            "end": 724,
                            "flags": 4227072,
                            "modifierFlagsCache": 0,
                            "transformFlags": 0,
                            "kind": 325,
                            "tagName": {
                                "pos": 712,
                                "end": 720,
                                "flags": 4227072,
                                "modifierFlagsCache": 0,
                                "transformFlags": 0,
                                "kind": 79,
                                "escapedText": "required"
                            },
                            "comment": ""
                        }
                    ],
                    "rawdescription": "\n\nButton contents\n\n",
                    "description": "<p>Button contents</p>\n",
                    "line": 40,
                    "type": "string",
                    "decorators": []
                },
                {
                    "name": "primary",
                    "defaultValue": "false",
                    "deprecated": false,
                    "deprecationMessage": "",
                    "rawdescription": "\n\nIs this the principal call to action on the page?\n",
                    "description": "<p>Is this the principal call to action on the page?</p>\n",
                    "line": 20,
                    "type": "boolean",
                    "decorators": []
                },
                {
                    "name": "size",
                    "defaultValue": "'medium'",
                    "deprecated": false,
                    "deprecationMessage": "",
                    "rawdescription": "\n\nHow large should the button be?\n",
                    "description": "<p>How large should the button be?</p>\n",
                    "line": 32,
                    "type": "\"small\" | \"medium\" | \"large\"",
                    "decorators": []
                }
            ],
            "outputsClass": [
                {
                    "name": "onClick",
                    "defaultValue": "new EventEmitter<Event>()",
                    "deprecated": false,
                    "deprecationMessage": "",
                    "rawdescription": "\n\nOptional click handler\n",
                    "description": "<p>Optional click handler</p>\n",
                    "line": 46,
                    "type": "EventEmitter"
                }
            ],
            "propertiesClass": [],
            "methodsClass": [],
            "deprecated": false,
            "deprecationMessage": "",
            "hostBindings": [],
            "hostListeners": [],
            "description": "",
            "rawdescription": "\n",
            "type": "component",
            "sourceCode": "import { Component, Input, Output, EventEmitter } from '@angular/core';\n\n@Component({\n  selector: 'storybook-button',\n  template: ` <button\n    type=\"button\"\n    (click)=\"onClick.emit($event)\"\n    [ngClass]=\"classes\"\n    [ngStyle]=\"{ 'background-color': backgroundColor }\"\n  >\n    {{ label }}\n  </button>`,\n  styleUrls: ['./button.css'],\n})\nexport default class ButtonComponent {\n  /**\n   * Is this the principal call to action on the page?\n   */\n  @Input()\n  primary = false;\n\n  /**\n   * What background color to use\n   */\n  @Input()\n  backgroundColor?: string;\n\n  /**\n   * How large should the button be?\n   */\n  @Input()\n  size: 'small' | 'medium' | 'large' = 'medium';\n\n  /**\n   * Button contents\n   *\n   * @required\n   */\n  @Input()\n  label = 'Button';\n\n  /**\n   * Optional click handler\n   */\n  @Output()\n  onClick = new EventEmitter<Event>();\n\n  public get classes(): string[] {\n    const mode = this.primary ? 'storybook-button--primary' : 'storybook-button--secondary';\n\n    return ['storybook-button', `storybook-button--${this.size}`, mode];\n  }\n}\n",
            "assetsDirs": [],
            "styleUrlsData": [
                {
                    "data": ".storybook-button {\n  font-family: 'Nunito Sans', 'Helvetica Neue', Helvetica, Arial, sans-serif;\n  font-weight: 700;\n  border: 0;\n  border-radius: 3em;\n  cursor: pointer;\n  display: inline-block;\n  line-height: 1;\n}\n.storybook-button--primary {\n  color: white;\n  background-color: #1ea7fd;\n}\n.storybook-button--secondary {\n  color: #333;\n  background-color: transparent;\n  box-shadow: rgba(0, 0, 0, 0.15) 0px 0px 0px 1px inset;\n}\n.storybook-button--small {\n  font-size: 12px;\n  padding: 10px 16px;\n}\n.storybook-button--medium {\n  font-size: 14px;\n  padding: 11px 20px;\n}\n.storybook-button--large {\n  font-size: 16px;\n  padding: 12px 24px;\n}\n",
                    "styleUrl": "./button.css"
                }
            ],
            "stylesData": "",
            "accessors": {
                "classes": {
                    "name": "classes",
                    "getSignature": {
                        "name": "classes",
                        "type": "[]",
                        "returnType": "string[]",
                        "line": 48
                    }
                }
            }
        },
        {
            "name": "ButtonComponent",
            "id": "component-ButtonComponent-159b07b76983ede98cd584efa1e6bdc82417cb5231142c8cd3e0d090fc41e38558b99dfe8e8e4dd51d2b99e391b76918f000e170678f179d1c2ce8dc6a60b52f-1",
            "file": "projects/pattern-lib/src/lib/button/button.component.ts",
            "encapsulation": [],
            "entryComponents": [],
            "inputs": [],
            "outputs": [],
            "providers": [],
            "selector": "pl-button",
            "styleUrls": [
                "./button.component.scss"
            ],
            "styles": [],
            "templateUrl": [
                "./button.component.html"
            ],
            "viewProviders": [],
            "inputsClass": [
                {
                    "name": "color",
                    "defaultValue": "'primary'",
                    "deprecated": false,
                    "deprecationMessage": "",
                    "line": 13,
                    "type": "ThemePalette",
                    "decorators": []
                },
                {
                    "name": "disabled",
                    "defaultValue": "false",
                    "deprecated": false,
                    "deprecationMessage": "",
                    "line": 14,
                    "type": "boolean",
                    "decorators": []
                },
                {
                    "name": "label",
                    "defaultValue": "'Text goes here'",
                    "deprecated": false,
                    "deprecationMessage": "",
                    "line": 12,
                    "type": "string | null",
                    "decorators": []
                }
            ],
            "outputsClass": [
                {
                    "name": "eventChange",
                    "defaultValue": "new EventEmitter()",
                    "deprecated": false,
                    "deprecationMessage": "",
                    "line": 15,
                    "type": "EventEmitter<any>"
                }
            ],
            "propertiesClass": [],
            "methodsClass": [
                {
                    "name": "ngOnInit",
                    "args": [],
                    "optional": false,
                    "returnType": "void",
                    "typeParameters": [],
                    "line": 17,
                    "deprecated": false,
                    "deprecationMessage": ""
                },
                {
                    "name": "onEventChange",
                    "args": [
                        {
                            "name": "event",
                            "type": "MouseEvent",
                            "deprecated": false,
                            "deprecationMessage": ""
                        }
                    ],
                    "optional": false,
                    "returnType": "void",
                    "typeParameters": [],
                    "line": 19,
                    "deprecated": false,
                    "deprecationMessage": "",
                    "jsdoctags": [
                        {
                            "name": "event",
                            "type": "MouseEvent",
                            "deprecated": false,
                            "deprecationMessage": "",
                            "tagName": {
                                "text": "param"
                            }
                        }
                    ]
                }
            ],
            "deprecated": false,
            "deprecationMessage": "",
            "hostBindings": [],
            "hostListeners": [],
            "description": "",
            "rawdescription": "\n",
            "type": "component",
            "sourceCode": "import { Component, EventEmitter, Input, OnInit, Output } from '@angular/core';\nimport { ThemePalette } from '@angular/material/core';\n\n@Component({\n  selector: 'pl-button',\n  templateUrl: './button.component.html',\n  styleUrls: ['./button.component.scss'],\n})\nexport class ButtonComponent implements OnInit {\n  constructor() {}\n\n  @Input() label: string | null = 'Text goes here';\n  @Input() color: ThemePalette = 'primary';\n  @Input() disabled: boolean = false;\n  @Output() eventChange: EventEmitter<any> = new EventEmitter();\n\n  ngOnInit(): void {}\n\n  onEventChange(event: MouseEvent) {\n    this.eventChange.emit(event);\n  }\n}\n",
            "assetsDirs": [],
            "styleUrlsData": [
                {
                    "data": "",
                    "styleUrl": "./button.component.scss"
                }
            ],
            "stylesData": "",
            "constructorObj": {
                "name": "constructor",
                "description": "",
                "deprecated": false,
                "deprecationMessage": "",
                "args": [],
                "line": 9
            },
            "implements": [
                "OnInit"
            ],
            "isDuplicate": true,
            "duplicateId": 1,
            "duplicateName": "ButtonComponent-1",
            "templateData": "<button\n  mat-button\n  [color]=\"color\"\n  [disabled]=\"disabled\"\n  (click)=\"onEventChange($event)\"\n>\n  {{ label }}\n</button>\n"
        },
        {
            "name": "ButtonRaisedComponent",
            "id": "component-ButtonRaisedComponent-542ada92e419d6b063de630e3b9b2b21f4b483dcc946b8578dafe56d21adcc718486bde2b37aafcc3a2a83d63756398ce3c883c9419793667668636194d65c6f",
            "file": "projects/pattern-lib/src/lib/button-raised/button-raised.component.ts",
            "encapsulation": [],
            "entryComponents": [],
            "inputs": [],
            "outputs": [],
            "providers": [],
            "selector": "pl-button-raised",
            "styleUrls": [
                "./button-raised.component.scss"
            ],
            "styles": [],
            "templateUrl": [
                "./button-raised.component.html"
            ],
            "viewProviders": [],
            "inputsClass": [
                {
                    "name": "color",
                    "defaultValue": "'primary'",
                    "deprecated": false,
                    "deprecationMessage": "",
                    "line": 13,
                    "type": "ThemePalette",
                    "decorators": []
                },
                {
                    "name": "disabled",
                    "defaultValue": "false",
                    "deprecated": false,
                    "deprecationMessage": "",
                    "line": 14,
                    "type": "boolean",
                    "decorators": []
                },
                {
                    "name": "label",
                    "defaultValue": "'Text goes here'",
                    "deprecated": false,
                    "deprecationMessage": "",
                    "line": 12,
                    "type": "string | null",
                    "decorators": []
                }
            ],
            "outputsClass": [
                {
                    "name": "eventChange",
                    "defaultValue": "new EventEmitter()",
                    "deprecated": false,
                    "deprecationMessage": "",
                    "line": 15,
                    "type": "EventEmitter<any>"
                }
            ],
            "propertiesClass": [],
            "methodsClass": [
                {
                    "name": "ngOnInit",
                    "args": [],
                    "optional": false,
                    "returnType": "void",
                    "typeParameters": [],
                    "line": 17,
                    "deprecated": false,
                    "deprecationMessage": ""
                },
                {
                    "name": "onEventChange",
                    "args": [
                        {
                            "name": "event",
                            "type": "MouseEvent",
                            "deprecated": false,
                            "deprecationMessage": ""
                        }
                    ],
                    "optional": false,
                    "returnType": "void",
                    "typeParameters": [],
                    "line": 19,
                    "deprecated": false,
                    "deprecationMessage": "",
                    "jsdoctags": [
                        {
                            "name": "event",
                            "type": "MouseEvent",
                            "deprecated": false,
                            "deprecationMessage": "",
                            "tagName": {
                                "text": "param"
                            }
                        }
                    ]
                }
            ],
            "deprecated": false,
            "deprecationMessage": "",
            "hostBindings": [],
            "hostListeners": [],
            "description": "",
            "rawdescription": "\n",
            "type": "component",
            "sourceCode": "import { Component, EventEmitter, Input, OnInit, Output } from '@angular/core';\nimport { ThemePalette } from '@angular/material/core';\n\n@Component({\n  selector: 'pl-button-raised',\n  templateUrl: './button-raised.component.html',\n  styleUrls: ['./button-raised.component.scss'],\n})\nexport class ButtonRaisedComponent implements OnInit {\n  constructor() {}\n\n  @Input() label: string | null = 'Text goes here';\n  @Input() color: ThemePalette = 'primary';\n  @Input() disabled: boolean = false;\n  @Output() eventChange: EventEmitter<any> = new EventEmitter();\n\n  ngOnInit(): void {}\n\n  onEventChange(event: MouseEvent) {\n    this.eventChange.emit(event);\n  }\n}\n",
            "assetsDirs": [],
            "styleUrlsData": [
                {
                    "data": "",
                    "styleUrl": "./button-raised.component.scss"
                }
            ],
            "stylesData": "",
            "constructorObj": {
                "name": "constructor",
                "description": "",
                "deprecated": false,
                "deprecationMessage": "",
                "args": [],
                "line": 9
            },
            "implements": [
                "OnInit"
            ],
            "templateData": "<button\n  mat-raised-button\n  [color]=\"color\"\n  [disabled]=\"disabled\"\n  (click)=\"onEventChange($event)\"\n>\n  {{ label }}\n</button>\n"
        },
        {
            "name": "ButtonStrokedComponent",
            "id": "component-ButtonStrokedComponent-764ae18d1643f32b84bf133076bf39f6088a0d6c1e624bea513aa413dae53c843d58fc8082c1ccfa70c02a38101e21c646fa409bdba805b7ea0c159924bb78a2",
            "file": "projects/pattern-lib/src/lib/button-stroked/button-stroked.component.ts",
            "encapsulation": [],
            "entryComponents": [],
            "inputs": [],
            "outputs": [],
            "providers": [],
            "selector": "pl-button-stroked",
            "styleUrls": [
                "./button-stroked.component.scss"
            ],
            "styles": [],
            "templateUrl": [
                "./button-stroked.component.html"
            ],
            "viewProviders": [],
            "inputsClass": [
                {
                    "name": "color",
                    "defaultValue": "'primary'",
                    "deprecated": false,
                    "deprecationMessage": "",
                    "line": 13,
                    "type": "ThemePalette",
                    "decorators": []
                },
                {
                    "name": "disabled",
                    "defaultValue": "false",
                    "deprecated": false,
                    "deprecationMessage": "",
                    "line": 14,
                    "type": "boolean",
                    "decorators": []
                },
                {
                    "name": "label",
                    "defaultValue": "'Text goes here'",
                    "deprecated": false,
                    "deprecationMessage": "",
                    "line": 12,
                    "type": "string | null",
                    "decorators": []
                }
            ],
            "outputsClass": [
                {
                    "name": "eventChange",
                    "defaultValue": "new EventEmitter()",
                    "deprecated": false,
                    "deprecationMessage": "",
                    "line": 15,
                    "type": "EventEmitter<any>"
                }
            ],
            "propertiesClass": [],
            "methodsClass": [
                {
                    "name": "ngOnInit",
                    "args": [],
                    "optional": false,
                    "returnType": "void",
                    "typeParameters": [],
                    "line": 17,
                    "deprecated": false,
                    "deprecationMessage": ""
                },
                {
                    "name": "onEventChange",
                    "args": [
                        {
                            "name": "event",
                            "type": "MouseEvent",
                            "deprecated": false,
                            "deprecationMessage": ""
                        }
                    ],
                    "optional": false,
                    "returnType": "void",
                    "typeParameters": [],
                    "line": 19,
                    "deprecated": false,
                    "deprecationMessage": "",
                    "jsdoctags": [
                        {
                            "name": "event",
                            "type": "MouseEvent",
                            "deprecated": false,
                            "deprecationMessage": "",
                            "tagName": {
                                "text": "param"
                            }
                        }
                    ]
                }
            ],
            "deprecated": false,
            "deprecationMessage": "",
            "hostBindings": [],
            "hostListeners": [],
            "description": "",
            "rawdescription": "\n",
            "type": "component",
            "sourceCode": "import { Component, EventEmitter, Input, OnInit, Output } from '@angular/core';\nimport { ThemePalette } from '@angular/material/core';\n\n@Component({\n  selector: 'pl-button-stroked',\n  templateUrl: './button-stroked.component.html',\n  styleUrls: ['./button-stroked.component.scss'],\n})\nexport class ButtonStrokedComponent implements OnInit {\n  constructor() {}\n\n  @Input() label: string | null = 'Text goes here';\n  @Input() color: ThemePalette = 'primary';\n  @Input() disabled: boolean = false;\n  @Output() eventChange: EventEmitter<any> = new EventEmitter();\n\n  ngOnInit(): void {}\n\n  onEventChange(event: MouseEvent) {\n    this.eventChange.emit(event);\n  }\n}\n",
            "assetsDirs": [],
            "styleUrlsData": [
                {
                    "data": "",
                    "styleUrl": "./button-stroked.component.scss"
                }
            ],
            "stylesData": "",
            "constructorObj": {
                "name": "constructor",
                "description": "",
                "deprecated": false,
                "deprecationMessage": "",
                "args": [],
                "line": 9
            },
            "implements": [
                "OnInit"
            ],
            "templateData": "<button\n  mat-stroked-button\n  [color]=\"color\"\n  [disabled]=\"disabled\"\n  (click)=\"onEventChange($event)\"\n>\n  {{ label }}\n</button>\n"
        },
        {
            "name": "HeaderComponent",
            "id": "component-HeaderComponent-a557eec14f72c438a8033301f4d6ce023e0a1844a3b06ec2b38794a612acc31735ae78a5ee10071b230c8c20d699eb914554e69d07ade54adb371da8efb464cc",
            "file": "stories/header.component.ts",
            "encapsulation": [],
            "entryComponents": [],
            "inputs": [],
            "outputs": [],
            "providers": [],
            "selector": "storybook-header",
            "styleUrls": [
                "./header.css"
            ],
            "styles": [],
            "template": "<header>    <div class=\"wrapper\">\n      <div>\n        <svg width=\"32\" height=\"32\" viewBox=\"0 0 32 32\" xmlns=\"http://www.w3.org/2000/svg\">\n          <g fill=\"none\" fillRule=\"evenodd\">\n            <path\n              d=\"M10 0h12a10 10 0 0110 10v12a10 10 0 01-10 10H10A10 10 0 010 22V10A10 10 0 0110 0z\"\n              fill=\"#FFF\"\n            />\n            <path\n              d=\"M5.3 10.6l10.4 6v11.1l-10.4-6v-11zm11.4-6.2l9.7 5.5-9.7 5.6V4.4z\"\n              fill=\"#555AB9\"\n            />\n            <path\n              d=\"M27.2 10.6v11.2l-10.5 6V16.5l10.5-6zM15.7 4.4v11L6 10l9.7-5.5z\"\n              fill=\"#91BAF8\"\n            />\n          </g>\n        </svg>\n        <h1>Acme</h1>\n      </div>\n      <div>\n        <div *ngIf=\"user\">\n          <span class=\"welcome\">\n            Welcome, <b>{{ user.name }}</b\n            >!\n          </span>\n          <storybook-button\n            *ngIf=\"user\"\n            size=\"small\"\n            (onClick)=\"onLogout.emit($event)\"\n            label=\"Log out\"\n          ></storybook-button>\n        </div>\n        <div *ngIf=\"!user\">\n          <storybook-button\n            *ngIf=\"!user\"\n            size=\"small\"\n            class=\"margin-left\"\n            (onClick)=\"onLogin.emit($event)\"\n            label=\"Log in\"\n          ></storybook-button>\n          <storybook-button\n            *ngIf=\"!user\"\n            primary\n            size=\"small\"\n            primary=\"true\"\n            class=\"margin-left\"\n            (onClick)=\"onCreateAccount.emit($event)\"\n            label=\"Sign up\"\n          ></storybook-button>\n        </div>\n      </div>\n    </div>\n  </header>",
            "templateUrl": [],
            "viewProviders": [],
            "inputsClass": [
                {
                    "name": "user",
                    "defaultValue": "null",
                    "deprecated": false,
                    "deprecationMessage": "",
                    "line": 65,
                    "type": "User | null",
                    "decorators": []
                }
            ],
            "outputsClass": [
                {
                    "name": "onCreateAccount",
                    "defaultValue": "new EventEmitter<Event>()",
                    "deprecated": false,
                    "deprecationMessage": "",
                    "line": 74,
                    "type": "EventEmitter"
                },
                {
                    "name": "onLogin",
                    "defaultValue": "new EventEmitter<Event>()",
                    "deprecated": false,
                    "deprecationMessage": "",
                    "line": 68,
                    "type": "EventEmitter"
                },
                {
                    "name": "onLogout",
                    "defaultValue": "new EventEmitter<Event>()",
                    "deprecated": false,
                    "deprecationMessage": "",
                    "line": 71,
                    "type": "EventEmitter"
                }
            ],
            "propertiesClass": [],
            "methodsClass": [],
            "deprecated": false,
            "deprecationMessage": "",
            "hostBindings": [],
            "hostListeners": [],
            "description": "",
            "rawdescription": "\n",
            "type": "component",
            "sourceCode": "import { Component, Input, Output, EventEmitter } from '@angular/core';\nimport { User } from './User';\n\n@Component({\n  selector: 'storybook-header',\n  template: `<header>\n    <div class=\"wrapper\">\n      <div>\n        <svg width=\"32\" height=\"32\" viewBox=\"0 0 32 32\" xmlns=\"http://www.w3.org/2000/svg\">\n          <g fill=\"none\" fillRule=\"evenodd\">\n            <path\n              d=\"M10 0h12a10 10 0 0110 10v12a10 10 0 01-10 10H10A10 10 0 010 22V10A10 10 0 0110 0z\"\n              fill=\"#FFF\"\n            />\n            <path\n              d=\"M5.3 10.6l10.4 6v11.1l-10.4-6v-11zm11.4-6.2l9.7 5.5-9.7 5.6V4.4z\"\n              fill=\"#555AB9\"\n            />\n            <path\n              d=\"M27.2 10.6v11.2l-10.5 6V16.5l10.5-6zM15.7 4.4v11L6 10l9.7-5.5z\"\n              fill=\"#91BAF8\"\n            />\n          </g>\n        </svg>\n        <h1>Acme</h1>\n      </div>\n      <div>\n        <div *ngIf=\"user\">\n          <span class=\"welcome\">\n            Welcome, <b>{{ user.name }}</b\n            >!\n          </span>\n          <storybook-button\n            *ngIf=\"user\"\n            size=\"small\"\n            (onClick)=\"onLogout.emit($event)\"\n            label=\"Log out\"\n          ></storybook-button>\n        </div>\n        <div *ngIf=\"!user\">\n          <storybook-button\n            *ngIf=\"!user\"\n            size=\"small\"\n            class=\"margin-left\"\n            (onClick)=\"onLogin.emit($event)\"\n            label=\"Log in\"\n          ></storybook-button>\n          <storybook-button\n            *ngIf=\"!user\"\n            primary\n            size=\"small\"\n            primary=\"true\"\n            class=\"margin-left\"\n            (onClick)=\"onCreateAccount.emit($event)\"\n            label=\"Sign up\"\n          ></storybook-button>\n        </div>\n      </div>\n    </div>\n  </header>`,\n  styleUrls: ['./header.css'],\n})\nexport default class HeaderComponent {\n  @Input()\n  user: User | null = null;\n\n  @Output()\n  onLogin = new EventEmitter<Event>();\n\n  @Output()\n  onLogout = new EventEmitter<Event>();\n\n  @Output()\n  onCreateAccount = new EventEmitter<Event>();\n}\n",
            "assetsDirs": [],
            "styleUrlsData": [
                {
                    "data": ".wrapper {\n  font-family: 'Nunito Sans', 'Helvetica Neue', Helvetica, Arial, sans-serif;\n  border-bottom: 1px solid rgba(0, 0, 0, 0.1);\n  padding: 15px 20px;\n  display: flex;\n  align-items: center;\n  justify-content: space-between;\n}\n\nsvg {\n  display: inline-block;\n  vertical-align: top;\n}\n\nh1 {\n  font-weight: 900;\n  font-size: 20px;\n  line-height: 1;\n  margin: 6px 0 6px 10px;\n  display: inline-block;\n  vertical-align: top;\n}\n\nbutton + button {\n  margin-left: 10px;\n}\n\n.welcome {\n  color: #333;\n  font-size: 14px;\n  margin-right: 10px;\n}\n",
                    "styleUrl": "./header.css"
                }
            ],
            "stylesData": ""
        },
        {
            "name": "PageComponent",
            "id": "component-PageComponent-7126d8c2607c946741c651482413b43feb72b2d63cac9d3ac173fde206a5e635eb4cdbf7ca7ac9327c7d4d05cf7ef619144c34c11609ad677081d0ee4e855064",
            "file": "stories/page.component.ts",
            "encapsulation": [],
            "entryComponents": [],
            "inputs": [],
            "outputs": [],
            "providers": [],
            "selector": "storybook-page",
            "styleUrls": [
                "./page.css"
            ],
            "styles": [],
            "template": "<article>    <storybook-header\n      [user]=\"user\"\n      (onLogout)=\"doLogout()\"\n      (onLogin)=\"doLogin()\"\n      (onCreateAccount)=\"doCreateAccount()\"\n    ></storybook-header>\n    <section>\n      <h2>Pages in Storybook</h2>\n      <p>\n        We recommend building UIs with a\n        <a href=\"https://componentdriven.org\" target=\"_blank\" rel=\"noopener noreferrer\">\n          <strong>component-driven</strong>\n        </a>\n        process starting with atomic components and ending with pages.\n      </p>\n      <p>\n        Render pages with mock data. This makes it easy to build and review page states without\n        needing to navigate to them in your app. Here are some handy patterns for managing page data\n        in Storybook:\n      </p>\n      <ul>\n        <li>\n          Use a higher-level connected component. Storybook helps you compose such data from the\n          \"args\" of child component stories\n        </li>\n        <li>\n          Assemble data in the page component from your services. You can mock these services out\n          using Storybook.\n        </li>\n      </ul>\n      <p>\n        Get a guided tutorial on component-driven development at\n        <a href=\"https://storybook.js.org/tutorials/\" target=\"_blank\" rel=\"noopener noreferrer\">\n          Storybook tutorials\n        </a>\n        . Read more in the\n        <a href=\"https://storybook.js.org/docs\" target=\"_blank\" rel=\"noopener noreferrer\"> docs </a>\n        .\n      </p>\n      <div class=\"tip-wrapper\">\n        <span class=\"tip\">Tip</span> Adjust the width of the canvas with the\n        <svg width=\"10\" height=\"10\" viewBox=\"0 0 12 12\" xmlns=\"http://www.w3.org/2000/svg\">\n          <g fill=\"none\" fillRule=\"evenodd\">\n            <path\n              d=\"M1.5 5.2h4.8c.3 0 .5.2.5.4v5.1c-.1.2-.3.3-.4.3H1.4a.5.5 0 01-.5-.4V5.7c0-.3.2-.5.5-.5zm0-2.1h6.9c.3 0 .5.2.5.4v7a.5.5 0 01-1 0V4H1.5a.5.5 0 010-1zm0-2.1h9c.3 0 .5.2.5.4v9.1a.5.5 0 01-1 0V2H1.5a.5.5 0 010-1zm4.3 5.2H2V10h3.8V6.2z\"\n              id=\"a\"\n              fill=\"#999\"\n            />\n          </g>\n        </svg>\n        Viewports addon in the toolbar\n      </div>\n    </section>\n  </article>",
            "templateUrl": [],
            "viewProviders": [],
            "inputsClass": [],
            "outputsClass": [],
            "propertiesClass": [
                {
                    "name": "user",
                    "defaultValue": "null",
                    "deprecated": false,
                    "deprecationMessage": "",
                    "type": "User | null",
                    "optional": false,
                    "description": "",
                    "line": 64
                }
            ],
            "methodsClass": [
                {
                    "name": "doCreateAccount",
                    "args": [],
                    "optional": false,
                    "returnType": "void",
                    "typeParameters": [],
                    "line": 74,
                    "deprecated": false,
                    "deprecationMessage": ""
                },
                {
                    "name": "doLogin",
                    "args": [],
                    "optional": false,
                    "returnType": "void",
                    "typeParameters": [],
                    "line": 70,
                    "deprecated": false,
                    "deprecationMessage": ""
                },
                {
                    "name": "doLogout",
                    "args": [],
                    "optional": false,
                    "returnType": "void",
                    "typeParameters": [],
                    "line": 66,
                    "deprecated": false,
                    "deprecationMessage": ""
                }
            ],
            "deprecated": false,
            "deprecationMessage": "",
            "hostBindings": [],
            "hostListeners": [],
            "description": "",
            "rawdescription": "\n",
            "type": "component",
            "sourceCode": "import { Component } from '@angular/core';\nimport { User } from './User';\n\n@Component({\n  selector: 'storybook-page',\n  template: `<article>\n    <storybook-header\n      [user]=\"user\"\n      (onLogout)=\"doLogout()\"\n      (onLogin)=\"doLogin()\"\n      (onCreateAccount)=\"doCreateAccount()\"\n    ></storybook-header>\n    <section>\n      <h2>Pages in Storybook</h2>\n      <p>\n        We recommend building UIs with a\n        <a href=\"https://componentdriven.org\" target=\"_blank\" rel=\"noopener noreferrer\">\n          <strong>component-driven</strong>\n        </a>\n        process starting with atomic components and ending with pages.\n      </p>\n      <p>\n        Render pages with mock data. This makes it easy to build and review page states without\n        needing to navigate to them in your app. Here are some handy patterns for managing page data\n        in Storybook:\n      </p>\n      <ul>\n        <li>\n          Use a higher-level connected component. Storybook helps you compose such data from the\n          \"args\" of child component stories\n        </li>\n        <li>\n          Assemble data in the page component from your services. You can mock these services out\n          using Storybook.\n        </li>\n      </ul>\n      <p>\n        Get a guided tutorial on component-driven development at\n        <a href=\"https://storybook.js.org/tutorials/\" target=\"_blank\" rel=\"noopener noreferrer\">\n          Storybook tutorials\n        </a>\n        . Read more in the\n        <a href=\"https://storybook.js.org/docs\" target=\"_blank\" rel=\"noopener noreferrer\"> docs </a>\n        .\n      </p>\n      <div class=\"tip-wrapper\">\n        <span class=\"tip\">Tip</span> Adjust the width of the canvas with the\n        <svg width=\"10\" height=\"10\" viewBox=\"0 0 12 12\" xmlns=\"http://www.w3.org/2000/svg\">\n          <g fill=\"none\" fillRule=\"evenodd\">\n            <path\n              d=\"M1.5 5.2h4.8c.3 0 .5.2.5.4v5.1c-.1.2-.3.3-.4.3H1.4a.5.5 0 01-.5-.4V5.7c0-.3.2-.5.5-.5zm0-2.1h6.9c.3 0 .5.2.5.4v7a.5.5 0 01-1 0V4H1.5a.5.5 0 010-1zm0-2.1h9c.3 0 .5.2.5.4v9.1a.5.5 0 01-1 0V2H1.5a.5.5 0 010-1zm4.3 5.2H2V10h3.8V6.2z\"\n              id=\"a\"\n              fill=\"#999\"\n            />\n          </g>\n        </svg>\n        Viewports addon in the toolbar\n      </div>\n    </section>\n  </article>`,\n  styleUrls: ['./page.css'],\n})\nexport default class PageComponent {\n  user: User | null = null;\n\n  doLogout() {\n    this.user = null;\n  }\n\n  doLogin() {\n    this.user = { name: 'Jane Doe' };\n  }\n\n  doCreateAccount() {\n    this.user = { name: 'Jane Doe' };\n  }\n}\n",
            "assetsDirs": [],
            "styleUrlsData": [
                {
                    "data": "section {\n  font-family: 'Nunito Sans', 'Helvetica Neue', Helvetica, Arial, sans-serif;\n  font-size: 14px;\n  line-height: 24px;\n  padding: 48px 20px;\n  margin: 0 auto;\n  max-width: 600px;\n  color: #333;\n}\n\nsection h2 {\n  font-weight: 900;\n  font-size: 32px;\n  line-height: 1;\n  margin: 0 0 4px;\n  display: inline-block;\n  vertical-align: top;\n}\n\nsection p {\n  margin: 1em 0;\n}\n\nsection a {\n  text-decoration: none;\n  color: #1ea7fd;\n}\n\nsection ul {\n  padding-left: 30px;\n  margin: 1em 0;\n}\n\nsection li {\n  margin-bottom: 8px;\n}\n\nsection .tip {\n  display: inline-block;\n  border-radius: 1em;\n  font-size: 11px;\n  line-height: 12px;\n  font-weight: 700;\n  background: #e7fdd8;\n  color: #66bf3c;\n  padding: 4px 12px;\n  margin-right: 10px;\n  vertical-align: top;\n}\n\nsection .tip-wrapper {\n  font-size: 13px;\n  line-height: 20px;\n  margin-top: 40px;\n  margin-bottom: 40px;\n}\n\nsection .tip-wrapper svg {\n  display: inline-block;\n  height: 12px;\n  width: 12px;\n  margin-right: 4px;\n  vertical-align: top;\n  margin-top: 3px;\n}\n\nsection .tip-wrapper svg path {\n  fill: #1ea7fd;\n}\n",
                    "styleUrl": "./page.css"
                }
            ],
            "stylesData": ""
        },
        {
            "name": "PatternLibComponent",
            "id": "component-PatternLibComponent-44e83aed784d74c184c293fb97c0ea247832263c86865d04d95650b986ff01bd5ee23b2f2fdb9bdb5cbdb6a687f6d3f98c66541ac0f5d7af316fea93a30514c4",
            "file": "projects/pattern-lib/src/lib/pattern-lib.component.ts",
            "encapsulation": [],
            "entryComponents": [],
            "inputs": [],
            "outputs": [],
            "providers": [],
            "selector": "pl-pattern-lib",
            "styleUrls": [],
            "styles": [],
            "template": "<p>\n  pattern-lib works!\n</p>\n",
            "templateUrl": [],
            "viewProviders": [],
            "inputsClass": [],
            "outputsClass": [],
            "propertiesClass": [],
            "methodsClass": [],
            "deprecated": false,
            "deprecationMessage": "",
            "hostBindings": [],
            "hostListeners": [],
            "description": "",
            "rawdescription": "\n",
            "type": "component",
            "sourceCode": "import { Component } from '@angular/core';\n\n@Component({\n  selector: 'pl-pattern-lib',\n  template: `\n    <p>\n      pattern-lib works!\n    </p>\n  `,\n  styles: [\n  ]\n})\nexport class PatternLibComponent {\n\n}\n",
            "assetsDirs": [],
            "styleUrlsData": "",
            "stylesData": ""
        }
    ],
    "modules": [
        {
            "name": "PatternLibModule",
            "id": "module-PatternLibModule-3c61ad893343b5d8e15bb9cbd5bb1b72be69d4a7106a6da569979a7c6cf6e26b425b2a3b39fb9440bd50c8910803a3e5831da51ae9d41cbed600f20fd7116ad8",
            "description": "",
            "deprecationMessage": "",
            "deprecated": false,
            "file": "projects/pattern-lib/src/lib/pattern-lib.module.ts",
            "methods": [],
            "sourceCode": "import { NgModule } from '@angular/core';\nimport { MatButtonModule } from '@angular/material/button';\nimport { ButtonComponent } from './button/button.component';\nimport { ButtonRaisedComponent } from './button-raised/button-raised.component';\nimport { ButtonStrokedComponent } from './button-stroked/button-stroked.component';\n\n@NgModule({\n  declarations: [\n    ButtonComponent,\n    ButtonRaisedComponent,\n    ButtonStrokedComponent,\n  ],\n  imports: [MatButtonModule],\n  exports: [ButtonComponent, ButtonRaisedComponent],\n})\nexport class PatternLibModule {}\n",
            "children": [
                {
                    "type": "providers",
                    "elements": []
                },
                {
                    "type": "declarations",
                    "elements": [
                        {
                            "name": "ButtonComponent"
                        },
                        {
                            "name": "ButtonRaisedComponent"
                        },
                        {
                            "name": "ButtonStrokedComponent"
                        }
                    ]
                },
                {
                    "type": "imports",
                    "elements": []
                },
                {
                    "type": "exports",
                    "elements": [
                        {
                            "name": "ButtonRaisedComponent"
                        }
                    ]
                },
                {
                    "type": "bootstrap",
                    "elements": []
                },
                {
                    "type": "classes",
                    "elements": []
                }
            ]
        }
    ],
    "miscellaneous": {
        "variables": [
            {
                "name": "Basic",
                "ctype": "miscellaneous",
                "subtype": "variable",
                "file": "stories/ButtonBasic.stories.tsx",
                "deprecated": false,
                "deprecationMessage": "",
                "type": "",
                "defaultValue": "Template.bind({})"
            },
            {
                "name": "Large",
                "ctype": "miscellaneous",
                "subtype": "variable",
                "file": "stories/Button.stories.ts",
                "deprecated": false,
                "deprecationMessage": "",
                "type": "",
                "defaultValue": "Template.bind({})"
            },
            {
                "name": "LoggedIn",
                "ctype": "miscellaneous",
                "subtype": "variable",
                "file": "stories/Header.stories.ts",
                "deprecated": false,
                "deprecationMessage": "",
                "type": "",
                "defaultValue": "Template.bind({})"
            },
            {
                "name": "LoggedIn",
                "ctype": "miscellaneous",
                "subtype": "variable",
                "file": "stories/Page.stories.ts",
                "deprecated": false,
                "deprecationMessage": "",
                "type": "",
                "defaultValue": "Template.bind({})"
            },
            {
                "name": "LoggedOut",
                "ctype": "miscellaneous",
                "subtype": "variable",
                "file": "stories/Header.stories.ts",
                "deprecated": false,
                "deprecationMessage": "",
                "type": "",
                "defaultValue": "Template.bind({})"
            },
            {
                "name": "LoggedOut",
                "ctype": "miscellaneous",
                "subtype": "variable",
                "file": "stories/Page.stories.ts",
                "deprecated": false,
                "deprecationMessage": "",
                "type": "",
                "defaultValue": "Template.bind({})"
            },
            {
                "name": "Primary",
                "ctype": "miscellaneous",
                "subtype": "variable",
                "file": "stories/Button.stories.ts",
                "deprecated": false,
                "deprecationMessage": "",
                "type": "",
                "defaultValue": "Template.bind({})"
            },
            {
                "name": "Raised",
                "ctype": "miscellaneous",
                "subtype": "variable",
                "file": "stories/ButtonRaised.stories.tsx",
                "deprecated": false,
                "deprecationMessage": "",
                "type": "",
                "defaultValue": "Template.bind({})"
            },
            {
                "name": "Secondary",
                "ctype": "miscellaneous",
                "subtype": "variable",
                "file": "stories/Button.stories.ts",
                "deprecated": false,
                "deprecationMessage": "",
                "type": "",
                "defaultValue": "Template.bind({})"
            },
            {
                "name": "Small",
                "ctype": "miscellaneous",
                "subtype": "variable",
                "file": "stories/Button.stories.ts",
                "deprecated": false,
                "deprecationMessage": "",
                "type": "",
                "defaultValue": "Template.bind({})"
            },
            {
                "name": "Stroked",
                "ctype": "miscellaneous",
                "subtype": "variable",
                "file": "stories/ButtonStroked.stories.tsx",
                "deprecated": false,
                "deprecationMessage": "",
                "type": "",
                "defaultValue": "Template.bind({})"
            },
            {
                "name": "Template",
                "ctype": "miscellaneous",
                "subtype": "variable",
                "file": "stories/Button.stories.ts",
                "deprecated": false,
                "deprecationMessage": "",
                "type": "Story<Button>",
                "defaultValue": "(args: Button) => ({\n  props: args,\n})"
            },
            {
                "name": "Template",
                "ctype": "miscellaneous",
                "subtype": "variable",
                "file": "stories/ButtonBasic.stories.tsx",
                "deprecated": false,
                "deprecationMessage": "",
                "type": "Story<ButtonComponent>",
                "defaultValue": "(args: ButtonComponent) => ({\n  component: ButtonComponent,\n  props: args,\n})"
            },
            {
                "name": "Template",
                "ctype": "miscellaneous",
                "subtype": "variable",
                "file": "stories/ButtonRaised.stories.tsx",
                "deprecated": false,
                "deprecationMessage": "",
                "type": "Story<ButtonRaisedComponent>",
                "defaultValue": "(\n  args: ButtonRaisedComponent\n) => ({\n  component: ButtonRaisedComponent,\n  props: args,\n})"
            },
            {
                "name": "Template",
                "ctype": "miscellaneous",
                "subtype": "variable",
                "file": "stories/ButtonStroked.stories.tsx",
                "deprecated": false,
                "deprecationMessage": "",
                "type": "Story<ButtonStrokedComponent>",
                "defaultValue": "(\n  args: ButtonStrokedComponent\n) => ({\n  component: ButtonStrokedComponent,\n  props: args,\n})"
            },
            {
                "name": "Template",
                "ctype": "miscellaneous",
                "subtype": "variable",
                "file": "stories/Header.stories.ts",
                "deprecated": false,
                "deprecationMessage": "",
                "type": "Story<Header>",
                "defaultValue": "(args: Header) => ({\n  props: args,\n})"
            },
            {
                "name": "Template",
                "ctype": "miscellaneous",
                "subtype": "variable",
                "file": "stories/Page.stories.ts",
                "deprecated": false,
                "deprecationMessage": "",
                "type": "Story<Page>",
                "defaultValue": "(args: Page) => ({\n  props: args,\n})"
            }
        ],
        "functions": [],
        "typealiases": [],
        "enumerations": [],
        "groupedVariables": {
            "stories/ButtonBasic.stories.tsx": [
                {
                    "name": "Basic",
                    "ctype": "miscellaneous",
                    "subtype": "variable",
                    "file": "stories/ButtonBasic.stories.tsx",
                    "deprecated": false,
                    "deprecationMessage": "",
                    "type": "",
                    "defaultValue": "Template.bind({})"
                },
                {
                    "name": "Template",
                    "ctype": "miscellaneous",
                    "subtype": "variable",
                    "file": "stories/ButtonBasic.stories.tsx",
                    "deprecated": false,
                    "deprecationMessage": "",
                    "type": "Story<ButtonComponent>",
                    "defaultValue": "(args: ButtonComponent) => ({\n  component: ButtonComponent,\n  props: args,\n})"
                }
            ],
            "stories/Button.stories.ts": [
                {
                    "name": "Large",
                    "ctype": "miscellaneous",
                    "subtype": "variable",
                    "file": "stories/Button.stories.ts",
                    "deprecated": false,
                    "deprecationMessage": "",
                    "type": "",
                    "defaultValue": "Template.bind({})"
                },
                {
                    "name": "Primary",
                    "ctype": "miscellaneous",
                    "subtype": "variable",
                    "file": "stories/Button.stories.ts",
                    "deprecated": false,
                    "deprecationMessage": "",
                    "type": "",
                    "defaultValue": "Template.bind({})"
                },
                {
                    "name": "Secondary",
                    "ctype": "miscellaneous",
                    "subtype": "variable",
                    "file": "stories/Button.stories.ts",
                    "deprecated": false,
                    "deprecationMessage": "",
                    "type": "",
                    "defaultValue": "Template.bind({})"
                },
                {
                    "name": "Small",
                    "ctype": "miscellaneous",
                    "subtype": "variable",
                    "file": "stories/Button.stories.ts",
                    "deprecated": false,
                    "deprecationMessage": "",
                    "type": "",
                    "defaultValue": "Template.bind({})"
                },
                {
                    "name": "Template",
                    "ctype": "miscellaneous",
                    "subtype": "variable",
                    "file": "stories/Button.stories.ts",
                    "deprecated": false,
                    "deprecationMessage": "",
                    "type": "Story<Button>",
                    "defaultValue": "(args: Button) => ({\n  props: args,\n})"
                }
            ],
            "stories/Header.stories.ts": [
                {
                    "name": "LoggedIn",
                    "ctype": "miscellaneous",
                    "subtype": "variable",
                    "file": "stories/Header.stories.ts",
                    "deprecated": false,
                    "deprecationMessage": "",
                    "type": "",
                    "defaultValue": "Template.bind({})"
                },
                {
                    "name": "LoggedOut",
                    "ctype": "miscellaneous",
                    "subtype": "variable",
                    "file": "stories/Header.stories.ts",
                    "deprecated": false,
                    "deprecationMessage": "",
                    "type": "",
                    "defaultValue": "Template.bind({})"
                },
                {
                    "name": "Template",
                    "ctype": "miscellaneous",
                    "subtype": "variable",
                    "file": "stories/Header.stories.ts",
                    "deprecated": false,
                    "deprecationMessage": "",
                    "type": "Story<Header>",
                    "defaultValue": "(args: Header) => ({\n  props: args,\n})"
                }
            ],
            "stories/Page.stories.ts": [
                {
                    "name": "LoggedIn",
                    "ctype": "miscellaneous",
                    "subtype": "variable",
                    "file": "stories/Page.stories.ts",
                    "deprecated": false,
                    "deprecationMessage": "",
                    "type": "",
                    "defaultValue": "Template.bind({})"
                },
                {
                    "name": "LoggedOut",
                    "ctype": "miscellaneous",
                    "subtype": "variable",
                    "file": "stories/Page.stories.ts",
                    "deprecated": false,
                    "deprecationMessage": "",
                    "type": "",
                    "defaultValue": "Template.bind({})"
                },
                {
                    "name": "Template",
                    "ctype": "miscellaneous",
                    "subtype": "variable",
                    "file": "stories/Page.stories.ts",
                    "deprecated": false,
                    "deprecationMessage": "",
                    "type": "Story<Page>",
                    "defaultValue": "(args: Page) => ({\n  props: args,\n})"
                }
            ],
            "stories/ButtonRaised.stories.tsx": [
                {
                    "name": "Raised",
                    "ctype": "miscellaneous",
                    "subtype": "variable",
                    "file": "stories/ButtonRaised.stories.tsx",
                    "deprecated": false,
                    "deprecationMessage": "",
                    "type": "",
                    "defaultValue": "Template.bind({})"
                },
                {
                    "name": "Template",
                    "ctype": "miscellaneous",
                    "subtype": "variable",
                    "file": "stories/ButtonRaised.stories.tsx",
                    "deprecated": false,
                    "deprecationMessage": "",
                    "type": "Story<ButtonRaisedComponent>",
                    "defaultValue": "(\n  args: ButtonRaisedComponent\n) => ({\n  component: ButtonRaisedComponent,\n  props: args,\n})"
                }
            ],
            "stories/ButtonStroked.stories.tsx": [
                {
                    "name": "Stroked",
                    "ctype": "miscellaneous",
                    "subtype": "variable",
                    "file": "stories/ButtonStroked.stories.tsx",
                    "deprecated": false,
                    "deprecationMessage": "",
                    "type": "",
                    "defaultValue": "Template.bind({})"
                },
                {
                    "name": "Template",
                    "ctype": "miscellaneous",
                    "subtype": "variable",
                    "file": "stories/ButtonStroked.stories.tsx",
                    "deprecated": false,
                    "deprecationMessage": "",
                    "type": "Story<ButtonStrokedComponent>",
                    "defaultValue": "(\n  args: ButtonStrokedComponent\n) => ({\n  component: ButtonStrokedComponent,\n  props: args,\n})"
                }
            ]
        },
        "groupedFunctions": {},
        "groupedEnumerations": {},
        "groupedTypeAliases": {}
    },
    "routes": [],
    "coverage": {
        "count": 3,
        "status": "low",
        "files": [
            {
                "filePath": "projects/pattern-lib/src/lib/button-raised/button-raised.component.ts",
                "type": "component",
                "linktype": "component",
                "name": "ButtonRaisedComponent",
                "coveragePercent": 0,
                "coverageCount": "0/8",
                "status": "low"
            },
            {
                "filePath": "projects/pattern-lib/src/lib/button-stroked/button-stroked.component.ts",
                "type": "component",
                "linktype": "component",
                "name": "ButtonStrokedComponent",
                "coveragePercent": 0,
                "coverageCount": "0/8",
                "status": "low"
            },
            {
                "filePath": "projects/pattern-lib/src/lib/button/button.component.ts",
                "type": "component",
                "linktype": "component",
                "name": "ButtonComponent",
                "coveragePercent": 0,
                "coverageCount": "0/8",
                "status": "low"
            },
            {
                "filePath": "projects/pattern-lib/src/lib/pattern-lib.component.ts",
                "type": "component",
                "linktype": "component",
                "name": "PatternLibComponent",
                "coveragePercent": 0,
                "coverageCount": "0/1",
                "status": "low"
            },
            {
                "filePath": "projects/pattern-lib/src/lib/pattern-lib.service.ts",
                "type": "injectable",
                "linktype": "injectable",
                "name": "PatternLibService",
                "coveragePercent": 0,
                "coverageCount": "0/2",
                "status": "low"
            },
            {
                "filePath": "stories/Button.stories.ts",
                "type": "variable",
                "linktype": "miscellaneous",
                "linksubtype": "variable",
                "name": "Large",
                "coveragePercent": 0,
                "coverageCount": "0/1",
                "status": "low"
            },
            {
                "filePath": "stories/Button.stories.ts",
                "type": "variable",
                "linktype": "miscellaneous",
                "linksubtype": "variable",
                "name": "Primary",
                "coveragePercent": 0,
                "coverageCount": "0/1",
                "status": "low"
            },
            {
                "filePath": "stories/Button.stories.ts",
                "type": "variable",
                "linktype": "miscellaneous",
                "linksubtype": "variable",
                "name": "Secondary",
                "coveragePercent": 0,
                "coverageCount": "0/1",
                "status": "low"
            },
            {
                "filePath": "stories/Button.stories.ts",
                "type": "variable",
                "linktype": "miscellaneous",
                "linksubtype": "variable",
                "name": "Small",
                "coveragePercent": 0,
                "coverageCount": "0/1",
                "status": "low"
            },
            {
                "filePath": "stories/Button.stories.ts",
                "type": "variable",
                "linktype": "miscellaneous",
                "linksubtype": "variable",
                "name": "Template",
                "coveragePercent": 0,
                "coverageCount": "0/1",
                "status": "low"
            },
            {
                "filePath": "stories/ButtonBasic.stories.tsx",
                "type": "variable",
                "linktype": "miscellaneous",
                "linksubtype": "variable",
                "name": "Basic",
                "coveragePercent": 0,
                "coverageCount": "0/1",
                "status": "low"
            },
            {
                "filePath": "stories/ButtonBasic.stories.tsx",
                "type": "variable",
                "linktype": "miscellaneous",
                "linksubtype": "variable",
                "name": "Template",
                "coveragePercent": 0,
                "coverageCount": "0/1",
                "status": "low"
            },
            {
                "filePath": "stories/ButtonRaised.stories.tsx",
                "type": "variable",
                "linktype": "miscellaneous",
                "linksubtype": "variable",
                "name": "Raised",
                "coveragePercent": 0,
                "coverageCount": "0/1",
                "status": "low"
            },
            {
                "filePath": "stories/ButtonRaised.stories.tsx",
                "type": "variable",
                "linktype": "miscellaneous",
                "linksubtype": "variable",
                "name": "Template",
                "coveragePercent": 0,
                "coverageCount": "0/1",
                "status": "low"
            },
            {
                "filePath": "stories/ButtonStroked.stories.tsx",
                "type": "variable",
                "linktype": "miscellaneous",
                "linksubtype": "variable",
                "name": "Stroked",
                "coveragePercent": 0,
                "coverageCount": "0/1",
                "status": "low"
            },
            {
                "filePath": "stories/ButtonStroked.stories.tsx",
                "type": "variable",
                "linktype": "miscellaneous",
                "linksubtype": "variable",
                "name": "Template",
                "coveragePercent": 0,
                "coverageCount": "0/1",
                "status": "low"
            },
            {
                "filePath": "stories/Header.stories.ts",
                "type": "variable",
                "linktype": "miscellaneous",
                "linksubtype": "variable",
                "name": "LoggedIn",
                "coveragePercent": 0,
                "coverageCount": "0/1",
                "status": "low"
            },
            {
                "filePath": "stories/Header.stories.ts",
                "type": "variable",
                "linktype": "miscellaneous",
                "linksubtype": "variable",
                "name": "LoggedOut",
                "coveragePercent": 0,
                "coverageCount": "0/1",
                "status": "low"
            },
            {
                "filePath": "stories/Header.stories.ts",
                "type": "variable",
                "linktype": "miscellaneous",
                "linksubtype": "variable",
                "name": "Template",
                "coveragePercent": 0,
                "coverageCount": "0/1",
                "status": "low"
            },
            {
                "filePath": "stories/Page.stories.ts",
                "type": "variable",
                "linktype": "miscellaneous",
                "linksubtype": "variable",
                "name": "LoggedIn",
                "coveragePercent": 0,
                "coverageCount": "0/1",
                "status": "low"
            },
            {
                "filePath": "stories/Page.stories.ts",
                "type": "variable",
                "linktype": "miscellaneous",
                "linksubtype": "variable",
                "name": "LoggedOut",
                "coveragePercent": 0,
                "coverageCount": "0/1",
                "status": "low"
            },
            {
                "filePath": "stories/Page.stories.ts",
                "type": "variable",
                "linktype": "miscellaneous",
                "linksubtype": "variable",
                "name": "Template",
                "coveragePercent": 0,
                "coverageCount": "0/1",
                "status": "low"
            },
            {
                "filePath": "stories/User.ts",
                "type": "interface",
                "linktype": "interface",
                "name": "User",
                "coveragePercent": 0,
                "coverageCount": "0/1",
                "status": "low"
            },
            {
                "filePath": "stories/button.component.ts",
                "type": "component",
                "linktype": "component",
                "name": "ButtonComponent",
                "coveragePercent": 83,
                "coverageCount": "5/6",
                "status": "very-good"
            },
            {
                "filePath": "stories/header.component.ts",
                "type": "component",
                "linktype": "component",
                "name": "HeaderComponent",
                "coveragePercent": 0,
                "coverageCount": "0/5",
                "status": "low"
            },
            {
                "filePath": "stories/page.component.ts",
                "type": "component",
                "linktype": "component",
                "name": "PageComponent",
                "coveragePercent": 0,
                "coverageCount": "0/5",
                "status": "low"
            }
        ]
    }
}